pyutilib.component.core-4.6.4-py2.7-nspkg.pth
pyutilib/component/core/__init__.py
pyutilib/component/core/core.py
pyutilib.component.core-4.6.4.dist-info/DESCRIPTION.rst
pyutilib.component.core-4.6.4.dist-info/METADATA
pyutilib.component.core-4.6.4.dist-info/metadata.json
pyutilib.component.core-4.6.4.dist-info/namespace_packages.txt
pyutilib.component.core-4.6.4.dist-info/RECORD
pyutilib.component.core-4.6.4.dist-info/top_level.txt
pyutilib.component.core-4.6.4.dist-info/WHEEL
