Metadata-Version: 1.1
Name: pyutilib.component.core
Version: 4.6.4
Summary: The PyUtilib Component Architecture.
Home-page: https://software.sandia.gov/svn/public/pyutilib/pyutilib.component.core
Author: William E. Hart
Author-email: wehart@sandia.gov
License: BSD
Keywords: utility
Platform: any
Classifier: Development Status :: 4 - Beta
Classifier: Intended Audience :: End Users/Desktop
Classifier: License :: OSI Approved :: BSD License
Classifier: Natural Language :: English
Classifier: Operating System :: Microsoft :: Windows
Classifier: Operating System :: Unix
Classifier: Programming Language :: Python
Classifier: Programming Language :: Unix Shell
Classifier: Topic :: Scientific/Engineering :: Mathematics
Classifier: Topic :: Software Development :: Libraries :: Python Modules
